LFE/__init__.py
LFE/extractor.py
LFE/features_set.py
LFE/text_processor.py
LFExtractor-1.0.1.dist-info/LICENSE
LFExtractor-1.0.1.dist-info/METADATA
LFExtractor-1.0.1.dist-info/WHEEL
LFExtractor-1.0.1.dist-info/top_level.txt
LFExtractor-1.0.1.dist-info/RECORD
