Metadata-Version: 2.1
Name: LFExtractor
Version: 1.0.1
Summary: A corpus-linguistic tool to extract and search for linguistic features
Home-page: https://github.com/jaaack-wang/ling_feature_extractor
Author: Jack Wang
Author-email: jackwang196531@gmail.com
License: MIT License
Keywords: Computational linguistics,Corpus-linguistic tool,NLP,Natural Language Processing
Platform: UNKNOWN
Classifier: Programming Language :: Python :: 3
Classifier: License :: OSI Approved :: MIT License
Classifier: Operating System :: OS Independent
Requires-Python: >=3.6
